{"meta": {"nDocuments": 35000, "dataset": "Million News Headlines", "k": 60}, "topics": [[0, "0.084*\"review\" + 0.082*\"title\" + 0.069*\"injured\" + 0.063*\"push\" + 0.052*\"bus\" + 0.048*\"warns\" + 0.045*\"care\" + 0.038*\"fed\" + 0.037*\"french\" + 0.036*\"n\""], [1, "0.178*\"court\" + 0.110*\"face\" + 0.060*\"time\" + 0.056*\"seeks\" + 0.048*\"four\" + 0.041*\"offer\" + 0.033*\"fishing\" + 0.032*\"sparks\" + 0.029*\"keep\" + 0.029*\"shooting\""], [2, "0.187*\"plan\" + 0.122*\"report\" + 0.054*\"funding\" + 0.039*\"research\" + 0.039*\"nuclear\" + 0.035*\"development\" + 0.029*\"round\" + 0.029*\"hill\" + 0.029*\"indonesian\" + 0.028*\"waste\""], [3, "0.131*\"get\" + 0.089*\"union\" + 0.080*\"teachers\" + 0.072*\"play\" + 0.063*\"telstra\" + 0.044*\"doubt\" + 0.042*\"shire\" + 0.040*\"price\" + 0.027*\"breaks\" + 0.023*\"travel\""], [4, "0.236*\"council\" + 0.132*\"qld\" + 0.061*\"found\" + 0.057*\"fight\" + 0.041*\"community\" + 0.034*\"land\" + 0.033*\"train\" + 0.032*\"mining\" + 0.029*\"youth\" + 0.024*\"crisis\""], [5, "0.099*\"farmers\" + 0.068*\"hope\" + 0.066*\"drought\" + 0.060*\"laws\" + 0.048*\"family\" + 0.041*\"new\" + 0.033*\"eight\" + 0.031*\"stand\" + 0.027*\"suicide\" + 0.027*\"meets\""], [6, "0.091*\"home\" + 0.086*\"funds\" + 0.068*\"claim\" + 0.059*\"study\" + 0.052*\"labor\" + 0.050*\"continue\" + 0.047*\"gm\" + 0.045*\"rail\" + 0.042*\"services\" + 0.036*\"find\""], [7, "0.165*\"open\" + 0.107*\"child\" + 0.078*\"record\" + 0.044*\"medical\" + 0.038*\"soldier\" + 0.037*\"sets\" + 0.031*\"doctor\" + 0.027*\"oil\" + 0.025*\"blamed\" + 0.022*\"birthday\""], [8, "0.144*\"wins\" + 0.089*\"public\" + 0.085*\"job\" + 0.073*\"bush\" + 0.065*\"urges\" + 0.044*\"saddam\" + 0.042*\"moves\" + 0.040*\"gas\" + 0.035*\"discuss\" + 0.029*\"highway\""], [9, "0.131*\"call\" + 0.124*\"killed\" + 0.094*\"two\" + 0.070*\"first\" + 0.058*\"pay\" + 0.055*\"england\" + 0.045*\"wont\" + 0.045*\"tax\" + 0.035*\"green\" + 0.031*\"offers\""], [10, "0.111*\"talks\" + 0.070*\"blast\" + 0.054*\"future\" + 0.050*\"school\" + 0.046*\"bomb\" + 0.045*\"cut\" + 0.044*\"house\" + 0.042*\"regional\" + 0.042*\"beckham\" + 0.033*\"puts\""], [11, "0.208*\"new\" + 0.071*\"british\" + 0.069*\"high\" + 0.055*\"hit\" + 0.054*\"backs\" + 0.033*\"battle\" + 0.027*\"start\" + 0.026*\"increase\" + 0.026*\"line\" + 0.025*\"challenge\""], [12, "0.152*\"death\" + 0.078*\"china\" + 0.072*\"return\" + 0.066*\"welcomes\" + 0.062*\"aust\" + 0.060*\"toll\" + 0.048*\"military\" + 0.037*\"rises\" + 0.033*\"looks\" + 0.028*\"finds\""], [13, "0.092*\"woman\" + 0.087*\"rejects\" + 0.086*\"takes\" + 0.064*\"airport\" + 0.062*\"residents\" + 0.054*\"national\" + 0.052*\"second\" + 0.038*\"dispute\" + 0.036*\"assault\" + 0.035*\"makes\""], [14, "0.099*\"mp\" + 0.057*\"threat\" + 0.056*\"wants\" + 0.054*\"israeli\" + 0.044*\"lose\" + 0.037*\"red\" + 0.035*\"williams\" + 0.032*\"tape\" + 0.030*\"benefit\" + 0.027*\"success\""], [15, "0.205*\"set\" + 0.065*\"row\" + 0.062*\"leaves\" + 0.046*\"kill\" + 0.042*\"terrorism\" + 0.038*\"staff\" + 0.036*\"ferry\" + 0.032*\"spark\" + 0.029*\"agreement\" + 0.028*\"11\""], [16, "0.103*\"australia\" + 0.095*\"lead\" + 0.070*\"year\" + 0.056*\"pakistan\" + 0.056*\"arrested\" + 0.056*\"un\" + 0.053*\"put\" + 0.046*\"india\" + 0.036*\"boat\" + 0.035*\"plane\""], [17, "0.124*\"still\" + 0.076*\"team\" + 0.056*\"aid\" + 0.055*\"cancer\" + 0.055*\"park\" + 0.039*\"jones\" + 0.036*\"army\" + 0.035*\"hunt\" + 0.030*\"police\" + 0.028*\"cleared\""], [18, "0.124*\"workers\" + 0.123*\"decision\" + 0.098*\"deal\" + 0.071*\"warning\" + 0.037*\"children\" + 0.036*\"shows\" + 0.030*\"list\" + 0.027*\"needs\" + 0.027*\"ama\" + 0.025*\"levy\""], [19, "0.124*\"former\" + 0.097*\"denies\" + 0.086*\"protest\" + 0.058*\"aboriginal\" + 0.052*\"ruddock\" + 0.043*\"embassy\" + 0.031*\"nurses\" + 0.029*\"tent\" + 0.029*\"today\" + 0.027*\"fans\""], [20, "0.080*\"trade\" + 0.073*\"charge\" + 0.068*\"bali\" + 0.060*\"accident\" + 0.058*\"legal\" + 0.056*\"accused\" + 0.033*\"bad\" + 0.032*\"triple\" + 0.028*\"nations\" + 0.027*\"awaits\""], [21, "0.091*\"rates\" + 0.077*\"planned\" + 0.069*\"stop\" + 0.055*\"plant\" + 0.048*\"concerned\" + 0.048*\"ethanol\" + 0.046*\"farm\" + 0.043*\"drop\" + 0.039*\"released\" + 0.033*\"wind\""], [22, "0.072*\"alleged\" + 0.047*\"race\" + 0.045*\"west\" + 0.043*\"reports\" + 0.043*\"councils\" + 0.042*\"break\" + 0.040*\"reef\" + 0.036*\"guilty\" + 0.035*\"issue\" + 0.035*\"interest\""], [23, "0.165*\"crash\" + 0.149*\"car\" + 0.077*\"air\" + 0.066*\"safety\" + 0.037*\"third\" + 0.026*\"qantas\" + 0.025*\"police\" + 0.023*\"across\" + 0.023*\"sales\" + 0.018*\"hands\""], [24, "0.135*\"may\" + 0.093*\"plans\" + 0.071*\"tourism\" + 0.061*\"end\" + 0.058*\"work\" + 0.041*\"body\" + 0.038*\"uni\" + 0.033*\"life\" + 0.030*\"market\" + 0.030*\"al\""], [25, "0.123*\"vic\" + 0.114*\"rise\" + 0.069*\"fears\" + 0.068*\"show\" + 0.046*\"japan\" + 0.040*\"states\" + 0.037*\"govt\" + 0.037*\"vows\" + 0.036*\"vote\" + 0.030*\"chinese\""], [26, "0.141*\"nsw\" + 0.082*\"missing\" + 0.058*\"budget\" + 0.058*\"gold\" + 0.052*\"police\" + 0.052*\"coast\" + 0.048*\"release\" + 0.046*\"search\" + 0.037*\"govt\" + 0.031*\"club\""], [27, "0.092*\"considers\" + 0.068*\"cuts\" + 0.067*\"soldiers\" + 0.058*\"crean\" + 0.054*\"alp\" + 0.049*\"defence\" + 0.046*\"bank\" + 0.039*\"ends\" + 0.038*\"media\" + 0.028*\"higher\""], [28, "0.095*\"korea\" + 0.068*\"told\" + 0.065*\"real\" + 0.053*\"anti\" + 0.046*\"players\" + 0.044*\"sale\" + 0.040*\"north\" + 0.033*\"parliament\" + 0.024*\"eye\" + 0.023*\"italian\""], [29, "0.131*\"fire\" + 0.074*\"road\" + 0.068*\"consider\" + 0.052*\"could\" + 0.046*\"victim\" + 0.041*\"bangladesh\" + 0.038*\"violence\" + 0.033*\"police\" + 0.030*\"baby\" + 0.030*\"begin\""], [30, "0.088*\"meeting\" + 0.084*\"ahead\" + 0.081*\"go\" + 0.063*\"begins\" + 0.061*\"palestinian\" + 0.055*\"questions\" + 0.040*\"season\" + 0.034*\"double\" + 0.027*\"wild\" + 0.025*\"arrive\""], [31, "0.153*\"nt\" + 0.087*\"bushfire\" + 0.052*\"victims\" + 0.052*\"target\" + 0.041*\"philippines\" + 0.036*\"efforts\" + 0.033*\"rescue\" + 0.032*\"bryant\" + 0.030*\"rescued\" + 0.030*\"bombing\""], [32, "0.184*\"inquiry\" + 0.075*\"hears\" + 0.065*\"strong\" + 0.056*\"jail\" + 0.041*\"dollar\" + 0.033*\"damage\" + 0.033*\"role\" + 0.033*\"semis\" + 0.026*\"coria\" + 0.017*\"submissions\""], [33, "0.217*\"says\" + 0.134*\"pm\" + 0.118*\"probe\" + 0.064*\"big\" + 0.042*\"mayor\" + 0.040*\"business\" + 0.031*\"police\" + 0.023*\"held\" + 0.021*\"launch\" + 0.021*\"league\""], [34, "0.107*\"dead\" + 0.070*\"faces\" + 0.069*\"australian\" + 0.045*\"say\" + 0.043*\"forces\" + 0.042*\"hits\" + 0.040*\"festival\" + 0.037*\"afl\" + 0.033*\"indian\" + 0.029*\"rebel\""], [35, "0.154*\"wa\" + 0.106*\"health\" + 0.100*\"group\" + 0.099*\"indigenous\" + 0.063*\"strike\" + 0.049*\"iraqi\" + 0.039*\"insurance\" + 0.028*\"medicare\" + 0.025*\"canberra\" + 0.017*\"cases\""], [36, "0.070*\"nats\" + 0.067*\"brisbane\" + 0.053*\"groups\" + 0.052*\"issues\" + 0.044*\"students\" + 0.040*\"senate\" + 0.039*\"looking\" + 0.038*\"official\" + 0.034*\"leadership\" + 0.030*\"talk\""], [37, "0.085*\"day\" + 0.074*\"expected\" + 0.068*\"clash\" + 0.060*\"g\" + 0.052*\"crown\" + 0.051*\"hobart\" + 0.034*\"dump\" + 0.034*\"womens\" + 0.030*\"compo\" + 0.024*\"stars\""], [38, "0.134*\"hospital\" + 0.108*\"industry\" + 0.040*\"people\" + 0.036*\"heads\" + 0.033*\"scores\" + 0.033*\"address\" + 0.031*\"agree\" + 0.030*\"marine\" + 0.030*\"visit\" + 0.028*\"host\""], [39, "0.131*\"attack\" + 0.093*\"troops\" + 0.082*\"north\" + 0.046*\"kills\" + 0.043*\"ready\" + 0.042*\"training\" + 0.038*\"downer\" + 0.037*\"stamp\" + 0.033*\"tigers\" + 0.030*\"give\""], [40, "0.119*\"tour\" + 0.096*\"security\" + 0.066*\"gets\" + 0.056*\"opposition\" + 0.050*\"track\" + 0.041*\"company\" + 0.038*\"project\" + 0.036*\"tough\" + 0.031*\"join\" + 0.027*\"debut\""], [41, "0.085*\"beattie\" + 0.061*\"finals\" + 0.054*\"hewitt\" + 0.049*\"indonesia\" + 0.043*\"fighting\" + 0.042*\"news\" + 0.037*\"rape\" + 0.035*\"asked\" + 0.035*\"tree\" + 0.034*\"meetings\""], [42, "0.080*\"murder\" + 0.065*\"bid\" + 0.063*\"final\" + 0.060*\"education\" + 0.049*\"years\" + 0.047*\"highlights\" + 0.047*\"restrictions\" + 0.040*\"rain\" + 0.035*\"water\" + 0.030*\"warned\""], [43, "0.093*\"sydney\" + 0.071*\"port\" + 0.061*\"jailed\" + 0.059*\"mine\" + 0.054*\"hold\" + 0.053*\"six\" + 0.033*\"ministers\" + 0.025*\"palestinians\" + 0.024*\"speaks\" + 0.024*\"come\""], [44, "0.074*\"armstrong\" + 0.071*\"free\" + 0.070*\"united\" + 0.066*\"woes\" + 0.061*\"bill\" + 0.052*\"fires\" + 0.044*\"planning\" + 0.036*\"want\" + 0.033*\"shortage\" + 0.024*\"drugs\""], [45, "0.178*\"govt\" + 0.083*\"help\" + 0.067*\"minister\" + 0.064*\"case\" + 0.053*\"hopes\" + 0.049*\"rebels\" + 0.039*\"meet\" + 0.033*\"local\" + 0.029*\"state\" + 0.027*\"blues\""], [46, "0.119*\"chief\" + 0.113*\"three\" + 0.057*\"weapons\" + 0.047*\"men\" + 0.036*\"another\" + 0.027*\"least\" + 0.025*\"1\" + 0.025*\"boy\" + 0.025*\"champions\" + 0.024*\"clears\""], [47, "0.123*\"back\" + 0.121*\"urged\" + 0.120*\"claims\" + 0.063*\"take\" + 0.058*\"centre\" + 0.051*\"aussie\" + 0.040*\"injury\" + 0.031*\"govt\" + 0.029*\"detention\" + 0.026*\"drivers\""], [48, "0.125*\"world\" + 0.096*\"cup\" + 0.086*\"ban\" + 0.071*\"changes\" + 0.067*\"south\" + 0.049*\"rules\" + 0.029*\"admits\" + 0.028*\"africa\" + 0.026*\"raid\" + 0.026*\"storm\""], [49, "0.163*\"act\" + 0.120*\"one\" + 0.049*\"five\" + 0.046*\"stay\" + 0.046*\"building\" + 0.040*\"management\" + 0.033*\"election\" + 0.033*\"control\" + 0.030*\"boss\" + 0.029*\"olympic\""], [50, "0.089*\"continues\" + 0.076*\"melbourne\" + 0.069*\"east\" + 0.054*\"last\" + 0.045*\"clean\" + 0.045*\"judge\" + 0.044*\"way\" + 0.041*\"long\" + 0.028*\"bans\" + 0.027*\"truck\""], [51, "0.163*\"win\" + 0.114*\"trial\" + 0.083*\"leader\" + 0.057*\"housing\" + 0.048*\"lions\" + 0.032*\"match\" + 0.032*\"response\" + 0.030*\"old\" + 0.029*\"dog\" + 0.025*\"aids\""], [52, "0.150*\"police\" + 0.102*\"support\" + 0.068*\"sex\" + 0.055*\"action\" + 0.045*\"seek\" + 0.038*\"investigate\" + 0.030*\"leaders\" + 0.026*\"racing\" + 0.025*\"post\" + 0.025*\"thorpe\""], [53, "0.124*\"charges\" + 0.076*\"victory\" + 0.060*\"good\" + 0.043*\"change\" + 0.042*\"risk\" + 0.035*\"evidence\" + 0.035*\"roddick\" + 0.034*\"journalist\" + 0.029*\"agrees\" + 0.028*\"expert\""], [54, "0.119*\"top\" + 0.062*\"darwin\" + 0.058*\"nz\" + 0.057*\"leave\" + 0.050*\"peace\" + 0.043*\"debate\" + 0.041*\"crime\" + 0.039*\"hicks\" + 0.035*\"ronaldinho\" + 0.035*\"slams\""], [55, "0.162*\"man\" + 0.080*\"tas\" + 0.066*\"charged\" + 0.061*\"dies\" + 0.059*\"aussies\" + 0.058*\"appeal\" + 0.045*\"confident\" + 0.045*\"move\" + 0.027*\"police\" + 0.020*\"board\""], [56, "0.136*\"concerns\" + 0.103*\"water\" + 0.091*\"calls\" + 0.079*\"sa\" + 0.062*\"defends\" + 0.040*\"howard\" + 0.037*\"govt\" + 0.036*\"rate\" + 0.033*\"focus\" + 0.026*\"blaze\""], [57, "0.118*\"iraq\" + 0.087*\"test\" + 0.077*\"force\" + 0.062*\"war\" + 0.047*\"make\" + 0.043*\"facing\" + 0.042*\"blair\" + 0.040*\"head\" + 0.037*\"iran\" + 0.027*\"party\""], [58, "0.472*\"us\" + 0.068*\"drug\" + 0.050*\"iraq\" + 0.028*\"king\" + 0.023*\"investigation\" + 0.022*\"iraqi\" + 0.022*\"uk\" + 0.020*\"predicts\" + 0.016*\"border\" + 0.015*\"son\""], [59, "0.146*\"boost\" + 0.087*\"power\" + 0.070*\"service\" + 0.050*\"station\" + 0.037*\"crows\" + 0.036*\"despite\" + 0.034*\"western\" + 0.032*\"campaign\" + 0.031*\"run\" + 0.030*\"eagles\""]], "empty_amount": 0, "empty_topics": []}